quforge/__init__.py
quforge/aux.py
quforge/circuit.py
quforge/cml.py
quforge/gates.py
quforge/optimizer.py
quforge/quforge.py
quforge/statevector.py
quforge-0.3.5.dist-info/LICENSE
quforge-0.3.5.dist-info/METADATA
quforge-0.3.5.dist-info/WHEEL
quforge-0.3.5.dist-info/top_level.txt
quforge-0.3.5.dist-info/RECORD
