Metadata-Version: 2.1
Name: quforge
Version: 0.3.5
Summary: QuForge: a library for qudit simulation
Home-page: https://github.com/tiago939/quforge
Author: Tiago de Souza Farias
Author-email: tiago.farias@ufscar.br
Classifier: Programming Language :: Python :: 3
Classifier: License :: OSI Approved :: Apache Software License
Classifier: Operating System :: OS Independent
Requires-Python: >=3.10
License-File: LICENSE
Requires-Dist: torch<3.0.0,>=2.0.1
Requires-Dist: numpy<2.0.0,>=1.26.4
